sp_tool/__init__.py
sp_tool/__main__.py
sp_tool/sharepoint/__init__.py
sp_tool/sharepoint/auth.py
sp_tool/sharepoint/connector.py
sp_tool/sharepoint/exceptions.py
sp_tool/sharepoint/url.py
sp_tool/sharepoint/utils.py
sp_tool/tool/__init__.py
sp_tool/tool/__main__.py
sp_tool/tool/file_lister.py
sp_tool/tool/logging.py
sp_tool/tool/main.py
sp_tool/tool/sp_tool.py
tests/__init__.py
tests/mock_logger.py
tests/test_sharepoint_url.py
tests/test_sharepoint_utils.py
sharepoint_tool-1.0.1.dist-info/LICENSE
sharepoint_tool-1.0.1.dist-info/METADATA
sharepoint_tool-1.0.1.dist-info/WHEEL
sharepoint_tool-1.0.1.dist-info/entry_points.txt
sharepoint_tool-1.0.1.dist-info/top_level.txt
sharepoint_tool-1.0.1.dist-info/RECORD
