Metadata-Version: 2.1
Name: sharepoint-tool
Version: 1.0.1
Summary: Sharepoint API Client for uploading to Sharepoint cloud instances
Home-page: https://mlasevich.github.io/sharepoint-tool/
Author: Michael Lasevich
Author-email: mlasevich@gmail.com
License: Apache 2.0
Platform: UNKNOWN
Classifier: Programming Language :: Python :: 3
Classifier: License :: OSI Approved :: Apache Software License
Classifier: Operating System :: OS Independent
Requires-Python: >=3.6
License-File: LICENSE
Requires-Dist: requests
Requires-Dist: PyYaml
Requires-Dist: click
